gitlablib/__init__.py
gitlablib/gitlab.py
gitlablib-0.1.dev0.dist-info/AUTHORS
gitlablib-0.1.dev0.dist-info/LICENSE
gitlablib-0.1.dev0.dist-info/METADATA
gitlablib-0.1.dev0.dist-info/WHEEL
gitlablib-0.1.dev0.dist-info/top_level.txt
gitlablib-0.1.dev0.dist-info/RECORD
