Metadata-Version: 2.1
Name: gitlablib
Version: 0.1.dev0
Summary: An unofficial Python 3 client for the GitLab API
Home-page: https://github.com/jdhp/gitlab-lib
Author: Jérémie DECOCK
Author-email: jd.jdhp@gmail.com
Project-URL: Bug Tracker, https://github.com/jdhp/gitlab-lib/issues
Keywords: gitlablib
Classifier: Development Status :: 4 - Beta
Classifier: Intended Audience :: Developers
Classifier: License :: OSI Approved :: MIT License
Classifier: Natural Language :: English
Classifier: Operating System :: OS Independent
Classifier: Programming Language :: Python :: 3
Classifier: Topic :: Software Development :: Libraries
Classifier: Topic :: Software Development :: Libraries :: Python Modules
Classifier: Topic :: Software Development :: Libraries :: Application Frameworks
Requires-Python: >=3.6
License-File: LICENSE
License-File: AUTHORS
